cubert/__init__.py
cubert/server.py
cubert-2025.5.25.1.dist-info/LICENSE
cubert-2025.5.25.1.dist-info/METADATA
cubert-2025.5.25.1.dist-info/WHEEL
cubert-2025.5.25.1.dist-info/entry_points.txt
cubert-2025.5.25.1.dist-info/RECORD
