Metadata-Version: 2.3
Name: cubert
Version: 2025.5.25.1
Summary: Network mapping
License: MIT
Keywords: scapy,networking
Author: walchko
Author-email: walchko@users.noreply.github.com
Requires-Python: >=3.10
Classifier: Development Status :: 4 - Beta
Classifier: Intended Audience :: Developers
Classifier: License :: OSI Approved :: MIT License
Classifier: Operating System :: OS Independent
Classifier: Programming Language :: Python :: 3
Classifier: Programming Language :: Python :: 3.10
Classifier: Programming Language :: Python :: 3.11
Classifier: Programming Language :: Python :: 3.12
Classifier: Programming Language :: Python :: 3.13
Classifier: Programming Language :: Python :: 3.14
Classifier: Topic :: Software Development :: Libraries
Classifier: Topic :: Software Development :: Libraries :: Application Frameworks
Classifier: Topic :: Software Development :: Libraries :: Python Modules
Requires-Dist: colorama
Requires-Dist: flask
Requires-Dist: pyyaml
Requires-Dist: scapy
Project-URL: Homepage, https://pypi.org/project/cubert/
Project-URL: Repository, https://github.com/AllGloryToTheHypnotoad/cubert
